[{"name":"黄超云","e_name":"cyhuang","email":"huangchaoyun@kugou.net"},{"name":"李长豪","e_name":"stefanli","email":"lichanghao@kugou.net"},{"name":"李子兴","e_name":"louisli","email":"lizixing@kugou.net"},{"name":"张小堡","e_name":"susaizhang","email":"zhangxiaobao@kugou.net"},{"name":"邱上保","e_name":"shangbaoqiu","email":""},{"name":"梁海龙","e_name":"rainliang","email":""},{"name":"祝绍坤","e_name":"shaokunzhu","email":"zhushaokun@kugou.net"},{"name":"梁杰明","e_name":"benjiliang","email":"liangjieming@kugou.net"},{"name":"漆绍和","e_name":"ericsqi","email":"qishaohe@kugou.net"},{"name":"赵崇杰","e_name":"cjzhao","email":"zhaochongjie@kugou.net"},{"name":"蒙云丰","e_name":"yunfengmeng","email":"mengyunfeng@kugou.net"},{"name":"卢天河","e_name":"timlu","email":"lutianhe@kugou.net"},{"name":"钟树坚","e_name":"kevenzhong","email":"zhongshujian@kugou.net"},{"name":"向燕军","e_name":"yanjunxiang","email":"yanjunxiang@kugou.net"},{"name":"邱勇","e_name":"radishqiu","email":"qiuyong@kugou.net"},{"name":"刘德华","e_name":"lookliu","email":"liudehua@kugou.net"},{"name":"任思豪","e_name":"howeren","email":"rensihao@kugou.net"},{"name":"张超论","e_name":"arthurzhang","email":"zhangchaolun@kugou.net"},{"name":"何源","e_name":"yuanhe","email":"heyuan@kugou.net"},{"name":"张杰","e_name":"jasonzhang","email":"zhangjie@kugou.net"},{"name":"杨晓东","e_name":"xiaodongyang","email":"yangxiaodong@kugou.net"},{"name":"张峰伟","e_name":"fengweizhang","email":"zhangfengwei@kugou.net"},{"name":"张明","e_name":"gemanzhang","email":""},{"name":"李健宁","e_name":"jianningli","email":"lijianning@kugou.net"},{"name":"李振东","e_name":"gandalfli","email":""},{"name":"邓龙生","e_name":null,"email":""},{"name":"刘超敏","e_name":null,"email":""},{"name":"苏楚杰","e_name":"cjsu","email":"suchujie@kugou.net"},{"name":"吴德伟","e_name":"davidwu","email":"wudewei@kugou.net"},{"name":"李永昌","e_name":"hugoli","email":"liyongchang@kugou.net"},{"name":"杨权新","e_name":"kendiyang","email":""},{"name":"钟其湘","e_name":"qixiangzhong","email":""},{"name":"刘日高","e_name":"rigaoliu","email":"liurigao@kugou.net"},{"name":"陈文锋","e_name":"cwfchen","email":"chenwenfeng@kugou.net"},{"name":"丁亮","e_name":"samding","email":"dingliang@kugou.net"},{"name":"黄成林","e_name":"chenglinhuang","email":"chenglinhuang@kugou.net"},{"name":"吴泽鑫","e_name":"jensenwu","email":"wuzexin@kugou.net"},{"name":"林桂升","e_name":"amylin","email":"linguisheng@kugou.net"},{"name":"林振杰","e_name":"jaykelin","email":""},{"name":"曹建龙","e_name":"","email":"caojianlong@kugou.net"},{"name":"胡岳文","e_name":"yuewenhu","email":"huyuewen@kugou.net"},{"name":"张思润","e_name":"leozhang","email":""},{"name":"李豪","e_name":"devilli","email":""},{"name":"曹景华","e_name":"andycao","email":""},{"name":"余旭东","e_name":"xudongyu","email":"xudongyu@kugou.net"},{"name":"张亮","e_name":"cavinzhang","email":"cavinzhang@kugou.net"},{"name":"黄美红","e_name":"merryhuang","email":""},{"name":"张龙海","e_name":null,"email":"zhanglonghai@kugou.net"},{"name":"甄超文","e_name":null,"email":"zhenchaowen@kugou.net"},{"name":"徐超","e_name":"crowxu","email":""},{"name":"黄旭彬","e_name":"xubinhuang","email":"huangxubin@kugou.net"},{"name":"何锐","e_name":null,"email":"herui@kugou.net"},{"name":"李鹏鹏","e_name":"pengpengli","email":"pengpengli@kugou.net"},{"name":"周媛媛","e_name":"wendyzhou","email":"zhouyuanyuan@kugou.net"},{"name":"黄德文","e_name":null,"email":"dewenhuang@kugou.net"},{"name":"刘明桃","e_name":"mingtaoliu","email":""},{"name":"邱宇扬","e_name":null,"email":"qiuyuyang@kugou.net"},{"name":"刘辛","e_name":"xinliu","email":"xinliu@kugou.net"},{"name":"胡文强","e_name":"wenqianghu","email":""},{"name":"戴育东","e_name":"yudai","email":"daiyudong@kugou.net"},{"name":"陈驹","e_name":null,"email":"ponychen@kugou.net"},{"name":"雷彦科","e_name":"leolei","email":"leiyanke@kugou.net"},{"name":"邹桂平","e_name":"yoyozou","email":"yoyozou@kugou.net"},{"name":"林荣耀","e_name":null,"email":"linrongyao@kugou.net"},{"name":"陈雪猷","e_name":null,"email":"chenxueyou@kugou.net"},{"name":"黄文怡","e_name":"wenyihuang","email":""},{"name":"李兴旺","e_name":"jimmyli","email":""},{"name":"王成亮","e_name":null,"email":"wangchengliang@kugou.net"},{"name":"","e_name":"","email":""},{"name":"罗栋","e_name":null,"email":"luodong@kugou.net"},{"name":"李毅","e_name":"terryli","email":"liyi@kugou.net"},{"name":"万东波","e_name":"davidwan","email":""},{"name":"邱思琪","e_name":null,"email":"qiusiqi@kugou.net"},{"name":"李跃辉","e_name":null,"email":"yuehuili@kugou.net"},{"name":"刘佳泽","e_name":null,"email":"andyliu@kugou.net"},{"name":"陈景娥","e_name":null,"email":"chenjinge@kugou.net"},{"name":"梁财杰","e_name":"caijieliang","email":""},{"name":"李焕雄","e_name":"huanxiongli","email":"lihuanxiong@kugou.net"},{"name":"伍继林","e_name":"jilinwu","email":""},{"name":"张伟宝","e_name":null,"email":"zhangweibao@kugou.net"},{"name":"黎炳宏","e_name":null,"email":"libinghong@kugou.net"},{"name":"曾佳","e_name":null,"email":"zengjia@kugou.net"},{"name":"陈雪红","e_name":"xuehongchen","email":"chenxuehong@kugou.net"},{"name":"朱肇洲","e_name":"zhaozhouzhu","email":""},{"name":"邹毅贤","e_name":null,"email":"zouyixian@kugou.net"},{"name":"叶美华","e_name":null,"email":"yemeihua@kugou.net"},{"name":"杨建军","e_name":null,"email":"yangjianjun@kugou.net"},{"name":"连丽辉","e_name":"lifylian","email":"lianlihui@kugou.net"},{"name":"宋文","e_name":"wensong","email":"songwen@kugou.net"},{"name":"周斌","e_name":null,"email":"zhoubin@kugou.net"},{"name":"陈梓洧","e_name":null,"email":"ziweichen@kugou.net"},{"name":"黄益权","e_name":"mannyhuang","email":""},{"name":"魏少锋","e_name":"wenskyswei","email":"wenskyswei@kugou.net"},{"name":"郭欢","e_name":"huanguo","email":"huanguo@kugou.net"},{"name":"王泽玮","e_name":"jewewang","email":"wangzewei@kugou.net"},{"name":"赵海英","e_name":"dollyzhao","email":"dollyzhao@kugou.net"},{"name":"郭美玲","e_name":null,"email":"guomeiling@kugou.net"},{"name":"李永发","e_name":null,"email":"liyongfa@kugou.net"},{"name":"林颖欣","e_name":"carolinelin","email":""},{"name":"唐永红","e_name":null,"email":"tangyonghong@kugou.net"},{"name":"柯淼","e_name":"mikeke","email":""},{"name":"陈啸","e_name":null,"email":"xiaochen@kugou.net"},{"name":"占文福","e_name":null,"email":"zhanwenfu@kugou.net"},{"name":"黄忠信","e_name":"shinhuang","email":""},{"name":"谭石强","e_name":"stonetan","email":"tanshiqiang@kugou.net"},{"name":"刘彬","e_name":"binliu","email":"liubin@kugou.net"},{"name":"李晓瑜","e_name":"evelycoili","email":""},{"name":"黄旋鑫","e_name":"xuanxinhuang","email":"xuanxinhuang@kugou.net"},{"name":"许云","e_name":"yunxu","email":"xuyun@kugou.net"},{"name":"陈毓","e_name":null,"email":"yuchen@kugou.net"},{"name":"刘维思","e_name":null,"email":"vcliu@kugou.net"},{"name":"杨胜坤","e_name":"skyang","email":""},{"name":"练家乐","e_name":"playinglian","email":""},{"name":"叶勤仿","e_name":"qinfangye","email":""},{"name":"监控助手","e_name":"monitor","email":""},{"name":"黎锦焕","e_name":"kimlee","email":"kimlee@kugou.net"},{"name":"黄志坚","e_name":"zhijianhuang","email":"huangzhijian@kugou.net"},{"name":"杜兴","e_name":"xingdu","email":""},{"name":"廖裕东","e_name":null,"email":"ansionliao@kugou.net"},{"name":"宋志诚","e_name":"travissong","email":"songzhicheng@kugou.net"},{"name":"张超钢","e_name":"chaogangzhang","email":"zhangchaogang@kugou.net"},{"name":"霍香玉","e_name":"xiangyuhuo","email":""},{"name":"禤锦良","e_name":null,"email":"xuanjinliang@kugou.net"},{"name":"刘文洁","e_name":"wenkyliu","email":"liuwenjie@kugou.net"},{"name":"邹志权","e_name":null,"email":"zouzhiquan@kugou.net"},{"name":"伍文波","e_name":"boriswu","email":""},{"name":"罗锦华","e_name":"jinhualuo","email":""},{"name":"陈晓如","e_name":"yiyichen","email":"chenxiaoru@kugou.net"},{"name":"李强1","e_name":"qianglee","email":""},{"name":"李思悦","e_name":"moonli","email":""},{"name":"钱程路","e_name":"chrisqian","email":"qianchenglu@kugou.net"},{"name":"陈成禧","e_name":"chengxichen","email":""},{"name":"阮陈贵","e_name":"leoruan","email":""},{"name":"许盛灿","e_name":null,"email":"xushengcan@kugou.net"},{"name":"谢少龙","e_name":"shaolongxie","email":""},{"name":"李松山","e_name":"anikoli","email":"anikoli@kugou.net"},{"name":"郑友韩","e_name":"johnzheng","email":"zhengyouhan@kugou.net"},{"name":"周波","e_name":"bobozhou","email":""},{"name":"杨以岸","e_name":"yeannyang","email":"yangyian@kugou.net"},{"name":"马敏蔚","e_name":null,"email":"kallenma@kugou.net"},{"name":"宁可","e_name":null,"email":"ningke@kugou.net"},{"name":"黄俊陆","e_name":"jhonnyhuang","email":"huangjunlu@kugou.net"},{"name":"邓锦豪","e_name":"jencoldeng","email":"dengjinhao@kugou.net"},{"name":"杨浩","e_name":null,"email":"haoyang@kugou.net"},{"name":"陈鸿","e_name":null,"email":"chenhong@kugou.net"},{"name":"何子杨","e_name":null,"email":"heziyang@kugou.net"},{"name":"李国煌","e_name":null,"email":"guohuangli@kugou.net"},{"name":"张秀萍","e_name":null,"email":"xiupingzhang@kugou.net"},{"name":"陆宝勤","e_name":"kenlu","email":"kenlu@kugou.net"},{"name":"杜绍豪","e_name":null,"email":"dushaohao@kugou.net"},{"name":"杨亚斌","e_name":"yabinyang","email":"yangyabin@kugou.net"},{"name":"曾慧玲","e_name":null,"email":"lin@kugou.net"},{"name":"梁文灏","e_name":"tomliang","email":""},{"name":"何荣珍","e_name":"rikohe","email":""},{"name":"冯万昌","e_name":"wanchangfeng","email":"fengwanchang@kugou.net"},{"name":"罗楠","e_name":"nickluo","email":"luonan@kugou.net"},{"name":"郑博开","e_name":"aboszheng","email":"aboszheng@kugou.net"},{"name":"肖纯智","e_name":"chunzhixiao","email":"xiaochunzhi@kugou.net"},{"name":"连敏杰","e_name":"jimmylian","email":"jimmylian@kugou.net"},{"name":"李碧莹","e_name":null,"email":"libiying@kugou.net"},{"name":"张晓杰","e_name":"paulzhang","email":"zhangxiaojie@kugou.net"},{"name":"关广才","e_name":"simenguan","email":"guanguangcai@kugou.net"},{"name":"潘廷稳","e_name":"sevenpan","email":"pantingwen@kugou.net"},{"name":"王鑫","e_name":"matildawang","email":"wangxin1@kugou.net"},{"name":"于彪斌","e_name":"maxyu","email":""},{"name":"王振","e_name":"morainwang","email":"morainwang@kugou.net"},{"name":"谢柳","e_name":"lewesxie","email":""},{"name":"梁恩同","e_name":"letekliang","email":""},{"name":"淳震华","e_name":"zhenhuachun","email":""},{"name":"曾先凤","e_name":"allyzeng","email":"zengxianfeng@kugou.net"},{"name":"石秀琼","e_name":"candyshi","email":"shiqiuqiong@kugou.net"},{"name":"张龄宇","e_name":"kenzhang","email":""},{"name":"钟建龙","e_name":"jianlongzhong","email":""},{"name":"黄志耿","e_name":"zhigenghuang","email":"zhigenghuang@kugou.net"},{"name":"王瑞期","e_name":"shahuwang","email":"shahuwang@kugou.net"},{"name":"吴剑明","e_name":"jianmingwu","email":"jianmingwu@kugou.net"},{"name":"王光宇","e_name":"guangyuwang","email":"guangyuwang@kugou.net"},{"name":"吴盛东","e_name":"shengdongwu","email":"wushengdong@kugou.net"},{"name":"黄铭志","e_name":"mingzhihuang","email":"huangmingzhi@kugou.net"},{"name":"常明","e_name":"adamchang","email":""},{"name":"刘永元","e_name":"lforxevercliu","email":""},{"name":"青绕藏格","e_name":"zanggeqingrao","email":""},{"name":"陈顶强","e_name":"dingqiangchen","email":""},{"name":"莫燊","e_name":"shanemo","email":"shanemo@kugou.net"},{"name":"胡博术","e_name":"ggbombhu","email":""},{"name":"陈志强","e_name":"zhiqiangchen","email":"zhiqiangchen@kugou.net"},{"name":"陈永星","e_name":"yongxingchen","email":""},{"name":"王虎","e_name":"forsythiawang","email":""},{"name":"张海波","e_name":"haibozhang","email":""},{"name":"林佳颂","e_name":"booleanlin","email":""},{"name":"杨远秋","e_name":"yuanqiuyang","email":"yuanqiuyang@kugou.net"},{"name":"侯毛显","e_name":"hlinhou","email":"houmaoxian@kugou.net"},{"name":"陈兆龙","e_name":"ginsbergchen","email":""},{"name":"徐晓婷","e_name":"xiaotingxu","email":""},{"name":"黄松盛","e_name":"songhuang","email":""},{"name":"王蹦","e_name":"simpsonwang","email":"wangbeng@kugou.net"},{"name":"黄泽锋","e_name":"maxhuang","email":"maxhuang@kugou.net"},{"name":"张君伟","e_name":"fishzhang","email":""},{"name":"区锦豪","e_name":"jinhaoou","email":"oujinhao@kugou.net"},{"name":"谭健文","e_name":"steventan","email":""},{"name":"张中云","e_name":"ericzhang","email":"zhangzhongyun@kugou.net"},{"name":"姚俊","e_name":"junyao","email":""},{"name":"梁锦涛","e_name":"jintaoliang","email":"liangjintao@kugou.net"},{"name":"黄健","e_name":"jamhuang","email":"jamhuang@kugou.net"},{"name":"林素娜","e_name":"sukilin","email":"linsuna@kugou.net"},{"name":"洪基明","e_name":"jimmyhong","email":""},{"name":"刘恒","e_name":"henleyliu","email":""},{"name":"赵忠","e_name":"zhongzhao","email":""},{"name":"丁扬健","e_name":"dexterding","email":""},{"name":"王伟佳","e_name":"weijiawang","email":"wangweijia@kugou.net"},{"name":"雷波","e_name":"leonlei","email":""},{"name":"熊一飞","e_name":"yifeixiong","email":""},{"name":"张萌","e_name":"mannyzhang","email":"mannyzhang@kugou.net"},{"name":"曾惜","e_name":"cindyzeng","email":""},{"name":"张越辉","e_name":"figozhang","email":"zhangyuehui@kugou.net"},{"name":"梁恩靖","e_name":"sophialiang","email":""},{"name":"许海波","e_name":"boilxu","email":""},{"name":"蔡谨潮","e_name":"allencai","email":"caijinchao@kugou.net"},{"name":"周啟暖","e_name":"qinuanzhou","email":""},{"name":"褚腾新","e_name":"vincentchu","email":"vincentchu@kugou.net"},{"name":"莫天乐","e_name":"tinlemo","email":"tinlemo@kugou.net"},{"name":"刘永惠","e_name":"ayuhiliu","email":"ayuhiliu@kugou.net"},{"name":"谢巍宇","e_name":"caryxie","email":""},{"name":"段智龙","e_name":"anlongduan","email":""},{"name":"卢健星","e_name":"kevinlu","email":""},{"name":"许太赐","e_name":"taicixu","email":"xutaici@kugou.net"},{"name":"雷虎","e_name":"ryanlei","email":""},{"name":"张娴","e_name":"xianzhang","email":"zhangxian@kugou.net"},{"name":"黎永兴","e_name":"yongxingli","email":""},{"name":"方敬武","e_name":"kinghoofang","email":""},{"name":"陈绍能","e_name":"shawnchen","email":"chenshaoneng@kugou.net"},{"name":"邹永","e_name":"tommy","email":"tommy@kugou.net"},{"name":"赵松","e_name":"songzhao","email":""},{"name":"陈光麒","e_name":"guangqichen","email":""},{"name":"林泽浜","e_name":"zebanglin","email":"zebanglin@kugou.net"},{"name":"林洪","e_name":"reddylin","email":""},{"name":"卢思宇","e_name":"lucylu","email":""},{"name":"王建标","e_name":"jamywang","email":"wangjianbiao@kugou.net"},{"name":"胡程宇","e_name":"chengyuhu","email":"huchengyu@kugou.net"},{"name":"李国宁","e_name":"guoningli","email":"liguoning@kugou.net"},{"name":"李海真","e_name":"tracerli","email":"lihaizhen@kugou.net"},{"name":"叶琛","e_name":"monicaye","email":""},{"name":"董曦","e_name":"jessedong","email":"dongxi@kugou.net"},{"name":"曾智旭","e_name":"zhixuzeng","email":"zengzhixu@kugou.net"},{"name":"黄德洋","e_name":"deyanghuang","email":""},{"name":"林壮宇","e_name":"zhuangyulin","email":"zhuangyulin@kugou.net"},{"name":"韦炳乐","e_name":"binglewei","email":""},{"name":"李树彬","e_name":"shubinli","email":"shubinli@kugou.net"},{"name":"丘敏丽","e_name":"minliqiu","email":""},{"name":"黄嘉沂","e_name":"o_devinhuang","email":""},{"name":"陈鹏宇","e_name":"pengyuchen","email":"pengyuchen@kugou.net"},{"name":"周红","e_name":"hongzhou","email":"hongzhou@kugou.net"},{"name":"曹挺","e_name":"tingcao","email":""},{"name":"李菁","e_name":"anneli","email":"lijing1@kugou.net"},{"name":"吴奕俊","e_name":"yijunwu","email":"yijunwu@kugou.net"},{"name":"吴昌贵","e_name":"changguiwu","email":""},{"name":"沈水兴","e_name":"shuixingshen","email":""},{"name":"梁浩钘","e_name":"carssunliang","email":""},{"name":"崔兆坤","e_name":"willingcui","email":"willingcui@kugou.net"},{"name":"沈达添","e_name":"datianshen","email":""},{"name":"杜维艳","e_name":"weiyandu","email":"duweiyan@kugou.net"},{"name":"陈喆","e_name":"nerochen","email":""},{"name":"李嘉明","e_name":"jiamingli","email":"jiamingli@kugou.net"},{"name":"陈文渊","e_name":"wenyuanchen","email":""},{"name":"郑凯鹏","e_name":"walkerzheng","email":"zhengkaipeng@kugou.net"},{"name":"甘波","e_name":"bobgan","email":"bobgan@kugou.net"},{"name":"徐伦","e_name":"larryxu","email":""},{"name":"林翔宇","e_name":"t_xiangyulin","email":""},{"name":"高宏业","e_name":"hongyegao","email":""},{"name":"黄日梅","e_name":"rimeihuang","email":"rimeihuang@kugou.net"},{"name":"李立宇","e_name":"liyuli","email":""},{"name":"袁春雨","e_name":"chunyuyuan","email":""},{"name":"欧百川","e_name":"baichuangou","email":""},{"name":"郭梓钿","e_name":"zitianguo","email":""},{"name":"辛悦","e_name":"yuexin","email":""},{"name":"刘博文","e_name":"bowenliu","email":"bowenliu@kugou.net"},{"name":"吴瑞平","e_name":"demowu","email":""},{"name":"陈于图","e_name":"yutuchen","email":""},{"name":"梁绮颖","e_name":"qiyingliang","email":""},{"name":"周沅轩","e_name":"yuanxuanzhou","email":"yuanxuanzhou@kugou.net"},{"name":"吴桐","e_name":"tonywu","email":""},{"name":"黄家明","e_name":"o_tobyhuang","email":""},{"name":"陈嘉豪","e_name":"jiahaochen","email":""},{"name":"张小红","e_name":"redzhang","email":"zhangxiaohong@kugou.net"},{"name":"林伟健","e_name":"weijianlin","email":"linweijian@kugou.net"},{"name":"李文","e_name":"levinlee","email":"liwen@kugou.net"},{"name":"莫志松","e_name":"jasonmo","email":"jasonmo@kugou.net"},{"name":"黄志","e_name":"neohuang","email":""},{"name":"伍威威","e_name":"wythewu","email":"wythewu@kugou.net"},{"name":"陈岳龙","e_name":"yuelongchen","email":""},{"name":"胡命文","e_name":"mingwenhu","email":"mingwenhu@kugou.net"},{"name":"卢灿","e_name":"allenlu","email":"allenlu@kugou.net"},{"name":"吴伟豪","e_name":"weihaowu","email":""},{"name":"叶润华","e_name":"lebronye","email":""},{"name":"刘家明","e_name":"jiamingliu","email":""},{"name":"吴梓栩","e_name":"sherlywu","email":""},{"name":"曾啟汛","e_name":"qixunzeng","email":""},{"name":"罗辉云","e_name":"huiyunluo","email":""},{"name":"李龙源","e_name":"longyuanli","email":"longyuanli@kugou.net"},{"name":"梁宇蕊","e_name":"yuruiliang","email":"yuruiliang@kugou.net"},{"name":"卜凡","e_name":"lanbu","email":""},{"name":"赵杏","e_name":"jessicazhao","email":"jessicazhao@kugou.net"},{"name":"谭绍恒","e_name":"tamtan","email":"tamtan@kugou.net"},{"name":"罗启军","e_name":"rexluo","email":""},{"name":"陈德林","e_name":"delamchen","email":""},{"name":"张锐","e_name":"janrayzhang","email":"janrayzhang@kugou.net"},{"name":"关宇博","e_name":"bertguan","email":""},{"name":"刘路","e_name":"liulu","email":""},{"name":"田威","e_name":"weitian","email":""},{"name":"袁再新","e_name":"zaixinyuan","email":""},{"name":"郭良纯","e_name":"liangchunguo","email":"liangchunguo@kugou.net"},{"name":"吴娜","e_name":"luffywu","email":""},{"name":"陈金源","e_name":"jinyuanchen","email":"chenjinyuan@kugou.net"},{"name":"王俊","e_name":"junwang","email":"wangjun@kugou.net"},{"name":"钟宝莹","e_name":"baoyingzhong","email":""},{"name":"黎国凯","e_name":"guokaili","email":""},{"name":"张钊明","e_name":"zhaomingzhang","email":""},{"name":"周徐波","e_name":"xubozhou","email":"zhouxubo@kugou.net"},{"name":"陈怡偲","e_name":"cosettechen","email":""},{"name":"林露","e_name":"lucylin","email":""},{"name":"谢导","e_name":"shadowxie","email":"shadowxie@kugou.net"},{"name":"明淑欣","e_name":"o_shuxinming","email":""},{"name":"欧阳孟明","e_name":"youngouyang","email":"ouyangmengming@kugou.net"},{"name":"邓东","e_name":"dongdeng","email":""},{"name":"刘玉龙","e_name":"yulongliu","email":""},{"name":"杨文婷","e_name":"cinkyyang","email":""},{"name":"刘佳欣","e_name":"kayanliu","email":"liujiaxin@kugou.net"},{"name":"陈凯","e_name":"kerwinhcen","email":""},{"name":"罗启斐","e_name":"jackluo","email":""},{"name":"曾昊","e_name":"alvinzeng","email":""},{"name":"董少华","e_name":"kendlingdong","email":"dongshaohua@kugou.net"},{"name":"许振雷","e_name":"zhenleixu","email":""},{"name":"陆丹莹","e_name":"danalu","email":""},{"name":"郭明慧","e_name":"dennisguo","email":""},{"name":"容健平","e_name":"jianpingrong","email":"jianpingrong@kugou.net"},{"name":"陈雄杰","e_name":"benbearchen","email":"chenxiongjie@kugou.net"},{"name":"何国型","e_name":"guoxinghe","email":"guoxinghe@kugou.net"},{"name":"梁嘉琪","e_name":"liangjiaqi","email":""},{"name":"吴向成","e_name":"hsiang","email":"hsiang@kugou.net"},{"name":"董经伟","e_name":"dondevi","email":""},{"name":"黄楚炎","e_name":"chuyanhuang","email":"huangchuyan@kugou.net"},{"name":"梁毅杰","e_name":"eakyliang","email":"eakyliang@kugou.net"},{"name":"陈自立","e_name":"zilichen","email":""},{"name":"李欣蕾","e_name":"xinleili","email":""},{"name":"潘洁霞","e_name":"chrispan","email":"chrispan@kugou.net"},{"name":"叶江楠","e_name":"jiangnanye","email":"jiangnanye@kugou.net"},{"name":"熊吉","e_name":"jixiong","email":"jixiong@kugou.net"},{"name":"钟育良","e_name":"xiaoliangzhong","email":"zhongyuliang@kugou.net"},{"name":"曹伟鹏","e_name":"frankycao","email":"frankycao@kugou.net"},{"name":"邱礼文","e_name":"levenqiu","email":"qiuliwen@kugou.net"},{"name":"汤伯超","e_name":"bochaotang","email":""},{"name":"段晋芳","e_name":"angeliaduan","email":"duanjinfang@kugou.net"},{"name":"韩晓丽","e_name":"xiaolihan","email":""},{"name":"吴芷盈","e_name":"cokiyawu","email":""},{"name":"唐灿江","e_name":"tomytang","email":"tomytang@kugou.net"},{"name":"周欣","e_name":"cicizhou","email":"cicizhou@kugou.net"},{"name":"黄星","e_name":"xinghuang","email":""},{"name":"李远晖","e_name":"henryli","email":"henryli@kugou.net"},{"name":"赵信","e_name":"xinzhao","email":""},{"name":"王琛","e_name":"jameswang","email":"jameswang@kugou.net"},{"name":"曾祥旭","e_name":"tomzeng","email":""},{"name":"黄仕强1","e_name":"foxhuang","email":"huangshiqiang1@kugou.net"},{"name":"梁艺慧","e_name":"viliceliang","email":""},{"name":"李帛骏","e_name":"bojunli","email":""},{"name":"洪梓旋","e_name":"zixuanhong","email":"zixuanhong@kugou.net"},{"name":"谢培阳","e_name":"peiyangxie","email":"peiyangxie@kugou.net"},{"name":"相里兴","e_name":"xingxiangli","email":"xingxiangli@kugou.net"},{"name":"张智鹏","e_name":"zhipengzhang","email":"zhipengzhang@kugou.net"},{"name":"蔡珉霞","e_name":"cathycai","email":""},{"name":"黄唐仁","e_name":"trhuang","email":""},{"name":"杨国花","e_name":"guohuayang","email":""},{"name":"黄涛","e_name":"nuanhuang","email":"nuanhuang@kugou.net"},{"name":"钟泱","e_name":"yangzhong","email":"yangzhong@kugou.net"},{"name":"陈岚","e_name":"kellandchen","email":"chenlan@kugou.net"},{"name":"杨晓光","e_name":"shineyang","email":"yangxiaoguang@kugou.net"},{"name":"钱红芳","e_name":"michelleqian","email":""},{"name":"罗伟","e_name":"reanluo","email":""},{"name":"陈华龙","e_name":"hualongchen","email":""},{"name":"周达和","e_name":"terryzhou","email":""},{"name":"余学刚","e_name":"xuegangyu","email":"xuegangyu@kugou.net"},{"name":"付苏","e_name":"aeronfu","email":""},{"name":"肖伟标","e_name":"bellxiao","email":""},{"name":"熊名男","e_name":"mingnanxiong","email":""},{"name":"王剑文","e_name":"jianwenwang","email":"jianwenwang@kugou.net"},{"name":"阮鸿波","e_name":"aronruan","email":"aronruan@kugou.net"},{"name":"陈映娜","e_name":"annachen","email":"annachen@kugou.net"},{"name":"杨鹏","e_name":"pengyang","email":"pengyang@kugou.net"},{"name":"陈伟杰","e_name":"weijiechen","email":"weijiechen@kugou.net"},{"name":"李振庆","e_name":"zhenqingli","email":""},{"name":"陈思桦","e_name":"o_suechen","email":""},{"name":"顾成东","e_name":"ericgu","email":""},{"name":"张晓旭","e_name":"sunzhang","email":"sunzhang@kugou.net"},{"name":"陈诗媛","e_name":"laurachen","email":""},{"name":"郭彩红","e_name":"caihongguo","email":""},{"name":"范苑","e_name":"freemanfan","email":""},{"name":"曾庆贤","e_name":"qingxianzeng","email":""},{"name":"江景敏","e_name":"kingmanjiang","email":"jiangjingmin@kugou.net"},{"name":"朱晓敏","e_name":"o_xiaominzhu","email":""},{"name":"李直","e_name":"t_leezhili","email":""},{"name":"徐春","e_name":"chunxu","email":"xuchun@kugou.net"},{"name":"周墩","e_name":"dunnzhou","email":"dunnzhou@kugou.net"},{"name":"屈永昌","e_name":"yongchangqu","email":"yongchangqu@kugou.net"},{"name":"黄国锴","e_name":"kimhuang","email":""},{"name":"周林军","e_name":"linjzhou","email":"zhoulinjun@kugou.net"},{"name":"周韬健","e_name":"tajokzhou","email":""},{"name":"胡镇华","e_name":"hopehu","email":""},{"name":"卢佳迪","e_name":"t_garylu","email":""},{"name":"黄志濠","e_name":"francishuang","email":"francishuang@kugou.net"},{"name":"许李俊","e_name":"lijunxu","email":""},{"name":"周志强","e_name":"zhouzhiqiang","email":""},{"name":"沈晶","e_name":"kikishen","email":""},{"name":"王婷","e_name":"estellewang","email":"estellewang@kugou.net"},{"name":"黎志江","e_name":"vincentli","email":"lizhijiang@kugou.net"},{"name":"关小敏","e_name":"shellguan","email":"guanxiaomin@kugou.net"},{"name":"林安锐","e_name":"anruilin","email":"anruilin@kugou.net"},{"name":"郭比仪","e_name":"biyiguo","email":""},{"name":"肖仲","e_name":"kensonxiao","email":""},{"name":"邱志光","e_name":"zhiguangqiu","email":"qiuzhiguang@kugou.net"},{"name":"涂梦坤","e_name":"andytu","email":"andytu@kugou.net"},{"name":"何仰提","e_name":"yangtihe","email":"yangtihe@kugou.net"},{"name":"黄裕佳","e_name":"yujiahuang","email":""},{"name":"欧阳小平","e_name":"snailouyang","email":"snailouyang@kugou.net"},{"name":"江永枫","e_name":"beckjiang","email":""},{"name":"刘什海","e_name":"shihailiu","email":"shihailiu@kugou.net"},{"name":"柳嘉欣","e_name":"jiaxinliu1","email":""},{"name":"林伟杰","e_name":"o_weijielin","email":""},{"name":"陈英杰","e_name":"yingjiechen","email":""},{"name":"祝磊","e_name":"leezhu","email":""},{"name":"朱云洁","e_name":"yunjiezhu","email":""},{"name":"梁政","e_name":"zhengliang","email":""},{"name":"张海洋","e_name":"harryzhang","email":""},{"name":"陈智勇","e_name":"zhiyongchen","email":""},{"name":"刘纯","e_name":"isobelliu","email":"liuchun@kugou.net"},{"name":"周炯彬","e_name":"jiongbinzhou","email":""},{"name":"李子彬","e_name":"derekli","email":"derekli@kugou.net"},{"name":"廖志毫","e_name":"t_joeliao","email":""},{"name":"林荣兴","e_name":"goodmorelin","email":""},{"name":"董容","e_name":"rongdong","email":"rongdong@kugou.net"},{"name":"陈永华","e_name":"yonghuachen","email":""},{"name":"李刚","e_name":"gangli","email":"gangli@kugou.net"},{"name":"刘俊鸿","e_name":"billyliu","email":""},{"name":"于晓飞","e_name":"xiaofeiyu","email":""},{"name":"杨帆","e_name":"tristayang","email":""},{"name":"陈俊成","e_name":"jcchen","email":""},{"name":"赖振奇","e_name":"zhenqilai","email":"zhenqilai@kugou.net"},{"name":"洪锐堉","e_name":"rockethong","email":"hongruiyu@kugou.net"},{"name":"何炜明","e_name":"weiminghe","email":""},{"name":"李有三","e_name":"yousanli","email":""},{"name":"廖秋丽","e_name":"qiuliliao","email":""},{"name":"罗毓新","e_name":"leoluo","email":""},{"name":"黄斌","e_name":"huangbin","email":""},{"name":"梁汝健","e_name":"valentineliang","email":""},{"name":"李佳林","e_name":"rebeccali","email":""},{"name":"潘蕾","e_name":"jerrypan","email":""},{"name":"陈睿","e_name":"forrychen","email":"forrychen@kugou.net"},{"name":"郑吉聪","e_name":"jedzheng","email":"jedzheng@kugou.net"},{"name":"杨思影","e_name":"siyingyang","email":"siyingyang@kugou.net"},{"name":"梁韵","e_name":"runnieliang","email":"runnieliang@kugou.net"},{"name":"吴成伟","e_name":"o_chengweiwu","email":""},{"name":"查理","e_name":"charliezha","email":""},{"name":"李楚俭","e_name":"alphalee","email":"lichujian@kugou.net"},{"name":"冼嘉颖","e_name":"jiayingxian","email":""},{"name":"吴芬芬","e_name":"fenfenwu","email":""},{"name":"周国涛","e_name":"guotaozhou","email":""},{"name":"卢宣宇","e_name":"bugoolu","email":"bugoolu@kugou.net"},{"name":"余乐鑫","e_name":"yoyu","email":""},{"name":"潘学基","e_name":"xuejipan","email":"xuejipan@kugou.net"},{"name":"邓文斌","e_name":"wenbindeng","email":""},{"name":"张定","e_name":"colinszhang","email":""},{"name":"张雪","e_name":"pt_alice","email":""},{"name":"张雪","e_name":"pt_alice","email":""},{"name":"李必涛","e_name":"brantlee","email":"brantlee@kugou.net"},{"name":"李必涛","e_name":"brantlee","email":"brantlee@kugou.net"},{"name":"冯巧丹","e_name":"qiaodanfeng","email":"fengqiaodan@kugou.net"},{"name":"吴鸿琦","e_name":"tracywu","email":"wuhongqi@kugou.net"},{"name":"邹榕","e_name":"rongzou","email":""},{"name":"杨婧","e_name":"miaomiaoyang","email":""},{"name":"揭凯雯","e_name":"kevinjie","email":"jiekaiwen@kugou.net"},{"name":"何俊彦","e_name":"surahe","email":""},{"name":"刘丹","e_name":"doraliu","email":"doraliu@kugou.net"},{"name":"徐耀","e_name":"yaoxu","email":""},{"name":"吴春茂","e_name":"chunnmaowu","email":""},{"name":"麦健康","e_name":"brominemai","email":""},{"name":"廖鸿","e_name":"hongliao","email":""},{"name":"梁伟彬","e_name":"kamliang","email":"kamliang@kugou.net"},{"name":"程雨露","e_name":"yoecheng","email":""},{"name":"江之林","e_name":"jerojiang","email":""},{"name":"姚梓琪","e_name":"yukiyao","email":"yukiyao@kugou.net"},{"name":"庞冠钦","e_name":"eddiepang","email":"eddiepang@kugou.net"},{"name":"李青艺","e_name":"crystalli","email":""},{"name":"王森","e_name":"wilsonwang","email":"wangsen@kugou.net"},{"name":"李创新","e_name":"chuangxinli","email":"lichuangxin@kugou.net"},{"name":"全民君","e_name":"aidenquan","email":""},{"name":"李阳阳","e_name":"jimmyleeli","email":"jimmyleeli@kugou.net"},{"name":"林彬","e_name":"robinlim","email":""},{"name":"钟伟煜","e_name":"o_weiyuzhong","email":""},{"name":"劳若韩","e_name":"ellanlao","email":""},{"name":"寸镇华","e_name":"zhenhuacun","email":"zhenhuacun@kugou.net"},{"name":"周如君","e_name":"rujunzhou","email":""},{"name":"林顺涛","e_name":"shuntaolin","email":""},{"name":"林智斌","e_name":"jerrylin","email":"jerrylin@kugou.net"},{"name":"李启明","e_name":"qimingli","email":"qimingli@kugou.net"},{"name":"卢文钊","e_name":"wzlu","email":""},{"name":"李伙荃","e_name":"huoquanli","email":""},{"name":"郑小仙","e_name":"abbeyzheng","email":""},{"name":"饶慧林","e_name":"flynnrao","email":"flynnrao@kugou.net"},{"name":"谭家俊","e_name":"junetan","email":"junetan@kugou.net"},{"name":"李佳锋","e_name":"jiafengli","email":""},{"name":"孔凡列","e_name":"gitkong","email":"gitkong@kugou.net"},{"name":"江东亮","e_name":"dongliangjiang","email":""},{"name":"黎冬维","e_name":"cooffeeli","email":"cooffeeli@kugou.net"},{"name":"曾繁荣","e_name":"ronrwinzeng","email":""},{"name":"冀全伟","e_name":"t_quanweiji","email":""},{"name":"周艳晖","e_name":"yanhuizhou","email":"yanhuizhou@kugou.net"},{"name":"张琬卿","e_name":"t_freyazhang","email":""},{"name":"钟庆添","e_name":"tinzhong","email":""},{"name":"谢国秋","e_name":"guoqiuxie","email":"guoqiuxie@kugou.net"},{"name":"林文荣","e_name":"samlin","email":"samlin@kugou.net"},{"name":"刘家骏","e_name":"clearloveliu","email":""},{"name":"江文海","e_name":"tomjiang","email":"jiangwenhai@kugou.net"},{"name":"何炜奕","e_name":"louishe","email":""},{"name":"林佳俊","e_name":"jiajunlin","email":"jiajunlin@kugou.net"},{"name":"杨宇","e_name":"t_yuyang","email":""},{"name":"宋亮亮","e_name":"panghusong","email":""},{"name":"冯文辉","e_name":"jokerfeng","email":""},{"name":"刘宁珂","e_name":"ningkeliu","email":"ningkeliu@kugou.net"},{"name":"陈增荣","e_name":"machealchen","email":"chenzengrong@kugou.net"},{"name":"赵文燕","e_name":"wenyanzzhao","email":""},{"name":"林晓伟","e_name":"thomaslin","email":""},{"name":"刘伟玲","e_name":"weilingliu","email":"weilingliu@kugou.net"},{"name":"陈斌斌","e_name":"benbbchen","email":""},{"name":"张镇焜","e_name":"zhenkunzhang","email":""},{"name":"于泽铭","e_name":"ericyu","email":""},{"name":"郑小琴","e_name":"joyzheng","email":""},{"name":"丘万快","e_name":"paulqiu","email":""},{"name":"张洋洋","e_name":"danielzhang","email":""},{"name":"韦洪雨","e_name":"whywei","email":""},{"name":"彭颖志","e_name":"yingzhipeng","email":""},{"name":"罗惠萍","e_name":"appleluo","email":"appleluo@kugou.net"},{"name":"申婧","e_name":"melodyshen","email":""},{"name":"徐锦源","e_name":"jaylenxu","email":""},{"name":"龙秋萍","e_name":"qiupinglong","email":""},{"name":"刘发明","e_name":"rajiraliu","email":""},{"name":"陈普森","e_name":"pschen","email":"chenpusen@kugou.net"},{"name":"漆原","e_name":"t_wesleyqi","email":""},{"name":"何越","e_name":"elliehe","email":""},{"name":"张思佛","e_name":"sifozhang","email":""},{"name":"林丹淇","e_name":"t_danqilin","email":""},{"name":"罗浩诚","e_name":"t_haochengluo","email":""},{"name":"洪坚浩","e_name":"answerhong","email":"answerhong@kugou.net"},{"name":"周昌雄","e_name":"louiszhou","email":""},{"name":"张培熙","e_name":"peixizhang","email":"peixizhang@kugou.net"},{"name":"刘怡","e_name":"emmaliu","email":"emmaliu@kugou.net"},{"name":"李彤彤","e_name":"tongtongli","email":"tongtongli@kugou.net"},{"name":"李经伟","e_name":"jingweili","email":""},{"name":"李一新","e_name":"rickli","email":"rickli@kugou.net"},{"name":"陆加孟","e_name":"jiamenglu","email":""},{"name":"彭予炤","e_name":"yuzhaopeng","email":"yuzhaopeng@kugou.net"},{"name":"罗志宁","e_name":"zhiningluo","email":""},{"name":"周展坤","e_name":"zhankunzhou","email":""},{"name":"黎春红","e_name":"o_chunhongli","email":"o_chunhongli@kugou.net"},{"name":"张璞","e_name":"paullzhang","email":"zhangpu@kugou.net"},{"name":"左隆湘","e_name":"jasonzuo","email":"zuolongxiang@kugou.net"},{"name":"范凤涛","e_name":"fathifan","email":"fathifan@kugou.net"},{"name":"黄育涵","e_name":"yuhanhuang","email":"yuhanhuang@kugou.net"},{"name":"贺宏达","e_name":"diamondhe","email":"diamondhe@kugou.net"},{"name":"曹菲","e_name":"fificao","email":""},{"name":"曹辉","e_name":"hogancao","email":""},{"name":"张爱兰","e_name":"o_ailanzhang","email":"o_ailanzhang@kugou.net"},{"name":"陈晓杰","e_name":"jackchchen","email":""},{"name":"梁玉琪","e_name":"yukiliang","email":""},{"name":"陈强","e_name":"alenchen","email":""},{"name":"刘水松","e_name":"chongzailiu","email":""},{"name":"徐立威","e_name":"liweixu","email":""},{"name":"阮进益","e_name":"jinyiruan","email":""},{"name":"吴嘉亮","e_name":"jialiangwu","email":""},{"name":"罗嗣骥","e_name":"sijiluo","email":"luosiji@kugou.net"},{"name":"廖良翌","e_name":"liangyiliao","email":"liangyiliao@kugou.net"},{"name":"陈庚","e_name":"carrchen","email":""},{"name":"倪斯琪","e_name":"sikini","email":"nisiqi@kugou.net"},{"name":"刘少伟","e_name":"rogerliu","email":""},{"name":"陈桂泰","e_name":"guitaichen","email":""},{"name":"刘晓根","e_name":"xiaogenliu","email":"xiaogenliu@kugou.net"},{"name":"周及时","e_name":"davidzhou","email":"davidzhou@kugou.net"},{"name":"党正军","e_name":"peterdang","email":""},{"name":"刘晗","e_name":"hanksliu","email":"hanksliu@kugou.net"},{"name":"张贯求","e_name":"guanqiuzhang","email":"guanqiuzhang@kugou.net"},{"name":"谢昭波","e_name":"starkxie","email":""},{"name":"曾文富","e_name":"bluegozeng","email":"bluegozeng@kugou.net"},{"name":"李骥骁","e_name":"luckyli","email":""},{"name":"周炎华","e_name":"ryanzhou","email":""},{"name":"郝雄山","e_name":"xiongshanhao","email":""},{"name":"卢海刚","e_name":"haiganglu","email":"haiganglu@kugou.net"},{"name":"尹鹏飞","e_name":"dafei","email":""},{"name":"尹浩","e_name":"haoyin","email":"haoyin@kugou.net"},{"name":"蔡超","e_name":"caichao","email":"caichao@kugou.net"},{"name":"唐峰康","e_name":"fengkangtang","email":"fengkangtang@kugou.net"},{"name":"罗懿","e_name":"yiluo","email":""},{"name":"戴奇","e_name":"qidai","email":"qidai@kugou.net"},{"name":"田先明","e_name":"xianmingtian","email":"xianmingtian@kugou.net"},{"name":"阳雄俊","e_name":"sunnyyang","email":""},{"name":"黄楚才","e_name":"chucaihuang","email":"chucaihuang@kugou.net"},{"name":"谢泽涛","e_name":"zetaoxie","email":"zetaoxie@kugou.net"},{"name":"林奕海","e_name":"yihailin","email":""},{"name":"饶鹭丰","e_name":"lancerao","email":""},{"name":"梁嘉辉","e_name":"chrisliang","email":""},{"name":"赵锦杰","e_name":"jinjiezhao","email":""},{"name":"陈文华","e_name":"ivychen","email":"ivychen@kugou.net"},{"name":"彭骋","e_name":"ericcpeng","email":"ericcpeng@kugou.net"},{"name":"陆伟","e_name":"weilu","email":"weilu@kugou.net"},{"name":"黄兵","e_name":"icehuang","email":"huangbing@kugou.net"},{"name":"何路生","e_name":"unicornhe","email":"unicornhe@kugou.net"},{"name":"李剑扬","e_name":"gimyeungli","email":"gimyeungli@kugou.net"},{"name":"赖世杰","e_name":"jaylai","email":""},{"name":"张广裕","e_name":"guangyuzhang","email":"guangyuzhang@kugou.net"},{"name":"邓棚云","e_name":"pengyundeng","email":""},{"name":"伍思铭","e_name":"simonsimingwu","email":""},{"name":"梁王凯","e_name":"weikingliang","email":"weikingliang@kugou.net"},{"name":"朱俊华","e_name":"junhuazhu","email":"junhuazhu@kugou.net"},{"name":"许健浩","e_name":"jianhaoxu","email":""},{"name":"陈建文","e_name":"jasonchen","email":"jasonchen@kugou.net"},{"name":"王培健","e_name":"pjwang","email":""},{"name":"梁业鹏","e_name":"yepengliang","email":""},{"name":"叶佳航","e_name":"jiahangye","email":""},{"name":"王文博","e_name":"phiwang","email":""},{"name":"胡燕远","e_name":"lucashu","email":""},{"name":"陈懿思","e_name":"esenchen","email":"chenyisi@kugou.net"},{"name":"洪喜填","e_name":"o_xitianhong","email":"o_xitianhong@kugou.net"},{"name":"骆庆福","e_name":"qingfuluo","email":"qingfuluo@kugou.net"},{"name":"陈永颜","e_name":"rickychen","email":""},{"name":"刘耀平","e_name":"yaopingliu","email":""},{"name":"张海晴","e_name":"o_haiqingzhang","email":""},{"name":"罗伟耀","e_name":"weiyaoluo","email":"weiyaoluo@kugou.net"},{"name":"彭旭辉","e_name":"sagexhpeng","email":""},{"name":"陈方正","e_name":"fangzhengchen","email":"fangzhengchen@kugou.net"},{"name":"杨杰","e_name":"o_jieyang","email":""},{"name":"冯健","e_name":"louisfeng","email":""},{"name":"孙亚特","e_name":"yatesun","email":""},{"name":"詹瀛鱼","e_name":"bluezhan","email":"bluezhan@kugou.net"},{"name":"周俊佳","e_name":"junjiazhou","email":"junjiazhou@kugou.net"},{"name":"高贝贝","e_name":"beibeigao","email":"beibeigao@kugou.net"},{"name":"辜森雄","e_name":"senxionggu","email":"senxionggu@kugou.net"},{"name":"梁嘉俊","e_name":"lewisliang","email":"lewisliang@kugou.net"},{"name":"魏莹莹","e_name":"miphawei","email":"miphawei@kugou.net"},{"name":"陈辉智","e_name":"wisdomchen","email":"wisdomchen@kugou.net"},{"name":"李旭锐","e_name":"xuruili","email":""},{"name":"何圣洲","e_name":"shengzhouhe","email":""},{"name":"陈杰伦","e_name":"jaychen","email":"jaychen@kugou.net"},{"name":"谢韵玲","e_name":"emalyxie","email":"xieyunling@kugou.net"},{"name":"张浩然","e_name":"hansonzhang","email":""},{"name":"黄宝兰","e_name":"baolanhuang","email":"baolanhuang@kugou.net"},{"name":"邓荣东","e_name":"milesdeng","email":""},{"name":"黄中毓","e_name":"sherhomhuang","email":"sherhomhuang@kugou.net"},{"name":"谢达","e_name":"darronxie","email":"darronxie@kugou.net"},{"name":"陈学聪","e_name":"xuecongchen","email":"xuecongchen@kugou.net"},{"name":"庄楚标","e_name":"chubiaozhuang","email":"chubiaozhuang@kugou.net"},{"name":"陈欣瑜","e_name":"luffychen","email":""},{"name":"陈文托","e_name":"wentuochen","email":""},{"name":"曾虹儒","e_name":"hurzeng","email":"hurzeng@kugou.net"},{"name":"王鋆","e_name":"hughwang","email":""},{"name":"黄文杰","e_name":"javierhuang","email":"javierhuang@kugou.net"},{"name":"朱勇","e_name":"t_curryzhu","email":""},{"name":"郑志芳","e_name":"zhifangzheng","email":""},{"name":"胡恺燊","e_name":"kerwinhu","email":"kerwinhu@kugou.net"},{"name":"陈竞钊","e_name":"jaochen","email":"jaochen@kugou.net"},{"name":"李敏诗","e_name":"minshili","email":"minshili@kugou.net"},{"name":"郭龙军","e_name":"grantguo","email":"grantguo@kugou.net"},{"name":"叶胜","e_name":"shengye","email":""},{"name":"李勇刚","e_name":"yonggangli","email":"yonggangli@kugou.net"},{"name":"阮梓坤","e_name":"zikunruan","email":"zikunruan@kugou.net"},{"name":"宁辉鹏","e_name":"o_huipengning","email":""},{"name":"简智峣","e_name":"ankerjian","email":"ankerjian@kugou.net"},{"name":"廖科雄","e_name":"kexiongliao","email":""},{"name":"李倩","e_name":"eugeneli","email":""},{"name":"陈星","e_name":"xingchen","email":"xingchen@kugou.net"},{"name":"刘松","e_name":"sidliu","email":""},{"name":"陈志靖","e_name":"jinchen","email":"jinchen@kugou.net"},{"name":"王子文","e_name":"damondzwwang","email":"damondzwwang@kugou.net"},{"name":"方攀","e_name":"panfang","email":"panfang@kugou.net"},{"name":"叶小凤","e_name":"phoenixye","email":"phoenixye@kugou.net"},{"name":"卢嘉恒","e_name":"gavinlu","email":""},{"name":"李颖","e_name":"yingli","email":""},{"name":"袁小岚","e_name":"o_xlyuan","email":"o_xlyuan@kugou.net"},{"name":"沈晓周","e_name":"xiaozhoushen","email":"shenxiaozhou@kugou.net"},{"name":"曾健","e_name":"jonahzeng","email":""},{"name":"刘玉敏","e_name":"yuminliu","email":"yuminliu@kugou.net"},{"name":"陈思凡","e_name":"sunfedchen","email":"sunfedchen@kugou.net"},{"name":"程立兴","e_name":"jetcheng","email":"chenglixing@kugou.net"},{"name":"洛晋申","e_name":"jasonjsluo","email":""},{"name":"黄杨潮","e_name":"kekyhuang","email":"huangyangchao@kugou.net"},{"name":"钟放杰","e_name":"jasonzhong","email":"zhongfangjie@kugou.net"},{"name":"廖观沛","e_name":"paulliao","email":"paulliao@kugou.net"},{"name":"侯凌","e_name":"michaelhou","email":"houling@kugou.net"},{"name":"陶钰钘","e_name":"tototao","email":""},{"name":"罗迪嘉","e_name":"jackyluo","email":"luodijia@kugou.net"},{"name":"刘泽南","e_name":"zenanliu","email":"zenanliu@kugou.net"},{"name":"江正","e_name":"zechjiang","email":""},{"name":"陈信伙","e_name":"o_xinhuochen","email":"o_xinhuochen@kugou.net"},{"name":"方祝南","e_name":"znfang","email":"znfang@kugou.net"},{"name":"李子豪","e_name":"zihaoli","email":""},{"name":"郗瑶颖","e_name":"yaoyingxi","email":"xiyaoying@kugou.net"},{"name":"林泽雄","e_name":"zexilin","email":"zexilin@kugou.net"},{"name":"陈海丹","e_name":"o_haidanchen","email":"o_haidanchen@kugou.net"},{"name":"黄圳源","e_name":"hazyhuang","email":"hazyhuang@kugou.net"},{"name":"徐醇","e_name":"lukexu","email":""},{"name":"贺述远","e_name":"stevenhe","email":""},{"name":"欧海明","e_name":"lucasou","email":""},{"name":"李静芯","e_name":"jingxinli","email":"jingxinli@kugou.net"},{"name":"黄梓峰","e_name":"roccohuang","email":"roccohuang@kugou.net"},{"name":"祝康力","e_name":"conleyzhu","email":"conleyzhu@kugou.net"},{"name":"刘素梅","e_name":"o_sumeiliu","email":"o_sumeiliu@kugou.net"},{"name":"曾钰","e_name":"clatazeng","email":""},{"name":"程景","e_name":"jingcheng","email":"jingcheng@kugou.net"},{"name":"庄海金","e_name":"haijinzhuang","email":"haijinzhuang@kugou.net"},{"name":"张作槐","e_name":"hisonzhang","email":""},{"name":"吴全贵","e_name":"quanguiwu","email":"quanguiwu@kugou.net"},{"name":"李少桂","e_name":"shaoguili","email":"shaoguili@kugou.net"},{"name":"黄群发","e_name":"qunfahuang","email":""},{"name":"孔祥科","e_name":"kevinkong","email":"kevinkong@kugou.net"},{"name":"廖乔勃","e_name":"qiaoboliao","email":""},{"name":"李龙杰","e_name":"longjieli","email":"longjieli@kugou.net"},{"name":"黄壮鹏","e_name":"zhuangpenghuang","email":""},{"name":"张日晨","e_name":"cczhang","email":"cczhang@kugou.net"},{"name":"李培林","e_name":"peilinli","email":""},{"name":"黄柳珊","e_name":"liushanhuang","email":"liushanhuang@kugou.net"},{"name":"洪海玲","e_name":"hailinghong","email":""},{"name":"许亚文","e_name":"yawenxu","email":"yawenxu@kugou.net"},{"name":"邹月明","e_name":"yuemingzou","email":"yuemingzou@kugou.net"},{"name":"梅李琼","e_name":"sondermei","email":"sondermei@kugou.net"},{"name":"吴晓东","e_name":"shawnwu","email":"shawnwu@kugou.net"},{"name":"潘见婷","e_name":"justinepan","email":"justinepan@kugou.net"},{"name":"田汸泽寰","e_name":"tracytian","email":"tracytian@kugou.net"},{"name":"高雅丽","e_name":"yaligao","email":""},{"name":"陈肖婷","e_name":"xiaotingchen","email":"chenxiaoting@kugou.net"},{"name":"雷枫培","e_name":"fengpeilei","email":""},{"name":"海水威","e_name":"shuiweihai","email":"shuiweihai@kugou.net"},{"name":"刘心雨","e_name":"kuraliu","email":"kuraliu@kugou.net"},{"name":"何彦志","e_name":"yanzhihe","email":""},{"name":"吴东鸿","e_name":"donghongwu","email":""},{"name":"李岱滨","e_name":"daibinli","email":"daibinli@kugou.net"},{"name":"罗国球","e_name":"jerryluo","email":"luoguoqiu@kugou.net"},{"name":"冯广杰","e_name":"jerryfeng","email":"jerryfeng@kugou.net"},{"name":"詹浪奇","e_name":"langqizhan","email":""},{"name":"曾晰铨","e_name":"siriuszeng","email":"siriuszeng@kugou.net"},{"name":"杨向东","e_name":"eadonyang","email":"eadonyang@kugou.net"},{"name":"王世豪","e_name":"shihaowang","email":"shihaowang@kugou.net"},{"name":"张水森","e_name":"nathanzhang","email":""},{"name":"洪旭","e_name":"brucehong","email":"brucehong@kugou.net"},{"name":"廖志","e_name":"zhiliao","email":"zhiliao@kugou.net"},{"name":"彭晓勇","e_name":"jamespxypeng","email":"jamespxypeng@kugou.net"},{"name":"叶登峰","e_name":"dengfengye","email":"dengfengye@kugou.net"},{"name":"龚展鸿","e_name":"zhanhonggong","email":"gongzhanhong@kugou.net"},{"name":"潘伟华","e_name":"pandapan","email":"pandapan@kugou.net"},{"name":"林晓丹","e_name":"irenexdlin","email":"irenexdlin@kugou.net"},{"name":"何杰","e_name":"jackjhe","email":"jackjhe@kugou.net"},{"name":"吕美莹","e_name":"maylv","email":"maylv@kugou.net"},{"name":"陈雯俐","e_name":"wenlichen","email":""},{"name":"朱哲韬","e_name":"zhetaozhu","email":"zhetaozhu@kugou.net"},{"name":"吴坤鑫","e_name":"kingsonwu","email":"kingsonwu@kugou.net"},{"name":"叶奕霞","e_name":"aryaye","email":"aryaye@kugou.net"},{"name":"魏泽鹏","e_name":"zepengwei","email":""},{"name":"张永威","e_name":"dawinzhang","email":""},{"name":"郑冬平","e_name":"dempezheng","email":"dempezheng@kugou.net"},{"name":"郑啟发","e_name":"firezheng","email":"firezheng@kugou.net"},{"name":"陈代远","e_name":"dyerchen","email":"dyerchen@kugou.net"},{"name":"梁帅","e_name":"masonliang","email":"masonliang@kugou.net"},{"name":"罗奎","e_name":"tankkluo","email":""},{"name":"汪德林","e_name":"delinwang","email":"wangdelin@kugou.net"},{"name":"王勇泽","e_name":"reidwang","email":"reidwang@kugou.net"},{"name":"胡添淇","e_name":"remonhu","email":""},{"name":"陈新涛","e_name":"xintaochen","email":"xintaochen@kugou.net"},{"name":"吴佳林","e_name":"aftonwu","email":"aftonwu@kugou.net"},{"name":"王易","e_name":"yiwang","email":""},{"name":"巫振华","e_name":"timwu","email":""},{"name":"周彬","e_name":"binzhou","email":"binzhou@kugou.net"},{"name":"卢礼煜","e_name":"konanlilu","email":"konanlilu@kugou.net"},{"name":"林棋","e_name":"thomaslqlin","email":""},{"name":"麦锦强","e_name":"jinqiangmai","email":""},{"name":"许坤源","e_name":"leoxu","email":""},{"name":"周永池","e_name":"evelynzhou","email":"evelynzhou@kugou.net"},{"name":"梁娟婵","e_name":"juanchanliang","email":""},{"name":"罗金连","e_name":"jinlianluo","email":"luojinlian@kugou.net"},{"name":"陈伟健","e_name":"weijianchen","email":"weijianchen@kugou.net"},{"name":"蔡鸿嘉","e_name":"hongjiacai","email":""},{"name":"彭炜","e_name":"weipeng","email":"pengwei@kugou.net"},{"name":"凡冲","e_name":"frankfan","email":"frankfan@kugou.net"},{"name":"徐龙涛","e_name":"garenxu","email":"garenxu@kugou.net"},{"name":"林秋嘉","e_name":"qiujialin","email":""},{"name":"徐吴栋","e_name":"davidxu","email":"davidxu@kugou.net"},{"name":"黄兆文","e_name":"zhaowenhuang","email":"zhaowenhuang@kugou.net"},{"name":"朱静怡","e_name":"jingyizhu","email":"jingyizhu@kugou.net"},{"name":"杜亚颐","e_name":"yayedu","email":"yayedu@kugou.net"},{"name":"杨洋","e_name":"shirleyyangyang","email":""},{"name":"陈铿","e_name":"hugokchen","email":"hugokchen@kugou.net"},{"name":"陈思海","e_name":"sihaichen","email":"sihaichen@kugou.net"},{"name":"叶银财","e_name":"tonyye","email":"tonyye@kugou.net"},{"name":"左想","e_name":"xiangzuo","email":"xiangzuo@kugou.net"},{"name":"钟宝健","e_name":"aboozhong","email":""},{"name":"余镇邦","e_name":"alexyu","email":""},{"name":"廖丹纯","e_name":"o_danchunliao","email":""},{"name":"谢洪","e_name":"kiddxie","email":"xiehong@kugou.net"},{"name":"李林波","e_name":"lyndonli","email":"lyndonli@kugou.net"},{"name":"甄景恩","e_name":"gingjanzhen","email":""},{"name":"卢靖怡","e_name":"elainelu","email":"elainelu@kugou.net"},{"name":"洪锦涛","e_name":"jintaohong","email":"jintaohong@kugou.net"},{"name":"李金福","e_name":"kinfli","email":""},{"name":"张攀","e_name":"dylanzhang","email":"dylanzhang@kugou.net"},{"name":"冯文锦","e_name":"wenjinfeng","email":""},{"name":"陈楠","e_name":"nannchen","email":"nannchen@kugou.net"},{"name":"潘汉浚","e_name":"hanjunpan","email":""},{"name":"何福毅","e_name":"fuyihe","email":"fuyihe@kugou.net"},{"name":"刘春宇","e_name":"parkliu","email":"parkliu@kugou.net"},{"name":"温天亮","e_name":"advancewen","email":"advancewen@kugou.net"},{"name":"张晓君","e_name":"evazhang","email":"evazhang@kugou.net"},{"name":"朱晋","e_name":"foxzhu","email":"zhujin@kugou.net"},{"name":"王鹏远","e_name":"rocwang","email":"rocwang@kugou.net"},{"name":"沈锐","e_name":"tigershen","email":"tigershen@kugou.net"},{"name":"杨科妍","e_name":"keyanyang","email":""},{"name":"张亚斌","e_name":"yabinzhang","email":"yabinzhang@kugou.net"},{"name":"谢国强","e_name":"guoqiangxie","email":"guoqiangxie@kugou.net"},{"name":"梁晓东","e_name":"jackdoliang","email":""},{"name":"黄智豪","e_name":"zhihaohuang","email":""},{"name":"黄泽彬","e_name":"javonhuang","email":"javonhuang@kugou.net"},{"name":"冯子华","e_name":"zihuafeng","email":"zihuafeng@kugou.net"},{"name":"朱明","e_name":"beckzhu","email":""},{"name":"庄嘉峰","e_name":"tonyzhuang","email":"tonyzhuang@kugou.net"},{"name":"邱路发","e_name":"lufeqiu","email":"lufeqiu@kugou.net"},{"name":"李睿鹏","e_name":"ruipengli","email":"ruipengli@kugou.net"},{"name":"崔虎","e_name":"messicui","email":""},{"name":"曾祥辉","e_name":"kiritszeng","email":"kiritszeng@kugou.net"},{"name":"高承熙","e_name":"t_chancygao","email":""},{"name":"冯旭闻","e_name":"xuwenfeng","email":"xuwenfeng@kugou.net"},{"name":"芮焕明","e_name":"richrui","email":""},{"name":"吴杰豪","e_name":"jiehaowu","email":"jiehaowu@kugou.net"},{"name":"林浩","e_name":"leooahlin","email":"leooahlin@kugou.net"},{"name":"郑翘志","e_name":"georgezheng","email":""},{"name":"文谊","e_name":"kylewen","email":"kylewen@kugou.net"},{"name":"付敏","e_name":"minfu","email":"minfu@kugou.net"},{"name":"林炳文","e_name":"ivanlin","email":"ivanlin@kugou.net"},{"name":"汤智尧","e_name":"zhiyaotang","email":"zhiyaotang@kugou.net"},{"name":"谢铃铃","e_name":"linglingxie","email":"linglingxie@kugou.net"},{"name":"邓怡祈","e_name":"zisdeng","email":"zisdeng@kugou.net"},{"name":"陈柏龙","e_name":"bailongchen","email":"bailongchen@kugou.net"},{"name":"李宏强","e_name":"honli","email":"honli@kugou.net"},{"name":"陈泽锐","e_name":"o_zeruichen","email":"o_zeruichen@kugou.net"},{"name":"潘润欢","e_name":"noahpan","email":"noahpan@kugou.net"},{"name":"丁华","e_name":"dannyding","email":"dannyding@kugou.net"},{"name":"康优良","e_name":"kylenkang","email":"kylenkang@kugou.net"},{"name":"陈镇美","e_name":"o_zmeichen","email":"o_zmeichen@kugou.net"},{"name":"王一振","e_name":"yizhenwang","email":"yizhenwang@kugou.net"},{"name":"马海华","e_name":"haihuama","email":"haihuama@kugou.net"},{"name":"张小荣","e_name":"rorozhang","email":"rorozhang@kugou.net"},{"name":"陈楚新","e_name":"chuxinchen","email":"chuxinchen@kugou.net"},{"name":"卿嘉俊","e_name":"t_jeromqing","email":""},{"name":"孔令华","e_name":"o_lingkong","email":"o_lingkong@kugou.net"},{"name":"陈婧","e_name":"o_jingcchen","email":"o_jingcchen@kugou.net"},{"name":"王杰龙","e_name":"jielongwang","email":"jielongwang@kugou.net"},{"name":"陈忠鹤","e_name":"zhonghechen","email":"zhonghechen@kugou.net"},{"name":"吴波","e_name":"arnoldwu","email":"arnoldwu@kugou.net"},{"name":"曹毅","e_name":"t_flashcao","email":""},{"name":"刘志强","e_name":"lysunliu","email":"lysunliu@kugou.net"},{"name":"林寿泽","e_name":"laurencelin","email":"linshouze@kugou.net"},{"name":"王维","e_name":"endenwang","email":"endenwang@kugou.net"},{"name":"陈诗敏","e_name":"shiminchen","email":"shiminchen@kugou.net"},{"name":"赖荣凤","e_name":"g_rongfenglai","email":"g_rongfenglai@kugou.net"},{"name":"陈景文","e_name":"jingwenxchen","email":"chenjingwen@kugou.net"},{"name":"章登柱","e_name":"t_dizzzhang","email":""},{"name":"杨吕祥","e_name":"lvxiangyang","email":"lvxiangyang@kugou.net"},{"name":"张柏铨","e_name":"sczhang","email":"sczhang@kugou.net"},{"name":"李云建","e_name":"rainightli","email":"rainightli@kugou.net"},{"name":"郭倪","e_name":"leonguo","email":"leonguo@kugou.net"},{"name":"陈泓池","e_name":"hongchichen","email":"hongchichen@kugou.net"},{"name":"张雨婷","e_name":"lizytzhang","email":"lizytzhang@kugou.net"},{"name":"吴泽杰","e_name":"zejiewu","email":"zejiewu@kugou.net"},{"name":"彭靖耘","e_name":"jingyunpeng","email":"jingyunpeng@kugou.net"},{"name":"陈文超","e_name":"michaelmcchen","email":"michaelmcchen@kugou.net"},{"name":"黄岳鹏","e_name":"franklyhuang","email":"franklyhuang@kugou.net"},{"name":"冯展尧","e_name":"zhanyaofeng","email":"zhanyaofeng@kugou.net"},{"name":"方芳","e_name":"iceyfang","email":"iceyfang@kugou.net"},{"name":"林颖","e_name":"t_leonaylin","email":"t_leonaylin@kugou.net"},{"name":"陈业勋","e_name":"evanchen","email":"evanchen@kugou.net"},{"name":"杜昊","e_name":"t_haodu","email":"t_haodu@kugou.net"},{"name":"唐日升","e_name":"thomsontang","email":"tangrisheng@kugou.net"},{"name":"缪晓鋆","e_name":"hiugwanmiao","email":"hiugwanmiao@kugou.net"},{"name":"张志龙","e_name":"g_alanzlzhang","email":"g_alanzlzhang@kugou.net"},{"name":"胡锦闰","e_name":"g_tylerhu","email":"g_tylerhu@kugou.net"},{"name":"练质彬","e_name":"zhibinlian","email":"zhibinlian@kugou.net"},{"name":"于江兴","e_name":"g_jiangxingyu","email":"g_jiangxingyu@kugou.net"},{"name":"庄炯权","e_name":"jasonzhuang","email":"jasonzhuang@kugou.net"},{"name":"杜嘉豪","e_name":"johnnydu","email":"johnnydu@kugou.net"},{"name":"吕坤","e_name":"kunlv","email":"kunlv@kugou.net"},{"name":"赵威","e_name":"marwzhao","email":"marwzhao@kugou.net"},{"name":"吴泽君","e_name":"g_zeluswu","email":"g_zeluswu@kugou.net"},{"name":"颜浩","e_name":"haoyan","email":"haoyan@kugou.net"},{"name":"王伟","e_name":"g_davidwwang","email":"g_davidwwang@kugou.net"},{"name":"梅寒","e_name":"gavinmei","email":"gavinmei@kugou.net"},{"name":"李鹏飞","e_name":"g_peterpfli","email":"g_peterpfli@kugou.net"},{"name":"叶植江","e_name":"kenye","email":"kenye@kugou.net"},{"name":"余群","e_name":"shoalyu","email":"yuqun@kugou.net"},{"name":"栗金海","e_name":"jinhaili","email":"jinhaili@kugou.net"},{"name":"刘守凯","e_name":"shoukailiu","email":"shoukailiu@kugou.net"},{"name":"詹志方","e_name":"zhifangzhan","email":"zhifangzhan@kugou.net"},{"name":"陈暄群","e_name":"xuanqunchen","email":"xuanqunchen@kugou.net"},{"name":"廖春涛","e_name":"springliao","email":"springliao@kugou.net"},{"name":"周国金","e_name":"g_jerriezhou","email":"g_jerriezhou@kugou.net"},{"name":"杨鑫","e_name":"xinyang","email":"xinyang@kugou.net"},{"name":"麦健荣","e_name":"garrymai","email":"garrymai@kugou.net"},{"name":"赵军鹏","e_name":"g_oceannzhao","email":"g_oceannzhao@kugou.net"},{"name":"廖美花","e_name":"meihualiao","email":"meihualiao@kugou.net"},{"name":"符钰","e_name":"yufu","email":"yufu@kugou.net"},{"name":"刘梓谦","e_name":"zedliu","email":"liuziqian@kugou.net"},{"name":"袁智武","e_name":"zhiwuyuan","email":"zhiwuyuan@kugou.net"},{"name":"李超","e_name":"johnli","email":"lichao@kugou.net"},{"name":"罗焕","e_name":"huanluo","email":"huanluo@kugou.net"},{"name":"杨嘉程","e_name":"caelanyang","email":"caelanyang@kugou.net"},{"name":"何其都","e_name":"qiduhe","email":"qiduhe@kugou.net"},{"name":"林洁","e_name":"janelin","email":"linjie@kugou.net"},{"name":"莫炳森","e_name":"leemo","email":"leemo@kugou.net"},{"name":"游奕奇","e_name":"t_yvoyqyou","email":"t_yvoyqyou@kugou.net"},{"name":"朱文乐","e_name":"edmondzhu","email":"edmondzhu@kugou.net"},{"name":"童明","e_name":"mingotong","email":"mingotong@kugou.net"},{"name":"李一鸣","e_name":"yimingli","email":"yimingli@kugou.net"},{"name":"李海涛","e_name":"haitaoli","email":"haitaoli@kugou.net"},{"name":"张天宇","e_name":"skymanzhang","email":""},{"name":"朱孔洋","e_name":"frankiezhu","email":""},{"name":"郝凌轶","e_name":"lingyihao","email":"lingyihao@kugou.net"},{"name":"卞焕铃","e_name":"o_hlbian","email":"o_hlbian@kugou.net"},{"name":"朱华锐","e_name":"haydenzhu","email":"haydenzhu@kugou.net"},{"name":"何伟业","e_name":"weiyehe","email":"weiyehe@kugou.net"},{"name":"吴烁坚","e_name":"deanwu","email":"deanwu@kugou.net"},{"name":"李冠戴","e_name":"o_guandaili","email":"o_guandaili@kugou.net"},{"name":"黎梓毅","e_name":"ziyili","email":"ziyili@kugou.net"},{"name":"朱镇越","e_name":"zhenyuezhu","email":"zhenyuezhu@kugou.net"},{"name":"李泳权","e_name":"yongquanli","email":"yongquanli@kugou.net"},{"name":"饶旋","e_name":"saberrao","email":"saberrao@tencent.com"},{"name":"韦恒","e_name":"rexwei","email":"weiheng@kugou.net"},{"name":"吴瑞生","e_name":"rasonwu","email":"rasonwu@kugou.net"},{"name":"官志荣","e_name":"o_zrguan","email":"o_zrguan@kugou.net"},{"name":"刘志亮","e_name":"zhiliangliu","email":"zhiliangliu@kugou.net"},{"name":"陈腾跃","e_name":"jydenchen","email":"jydenchen@tencentmusic.com"},{"name":"林祖杰","e_name":"lyricslin","email":"lyricslin@tencentmusic.com"},{"name":"李革委","e_name":"regli","email":"regli@tencent.com"},{"name":"钟冰杰","e_name":"freezingzhong","email":"freezingzhong@kugou.net"},{"name":"刘付伟明","e_name":"wmliufu","email":"wmliufu@kugou.net"},{"name":"黄忆杭","e_name":"yihanghuang","email":"yihanghuang@kugou.net"},{"name":"陈曦","e_name":"sevenchen","email":"sevenchen@kugou.net"},{"name":"刘宇婷","e_name":"katarinaliu","email":"katarinaliu@kugou.net"},{"name":"徐鸿权","e_name":"hongquanxu","email":"hongquanxu@kugou.net"},{"name":"许慈銮","e_name":"chrisxu","email":"chrisxu@kugou.net"},{"name":"李启华","e_name":"qihuali","email":"qihuali@kugou.net"},{"name":"蔡陆培","e_name":"lupeicai","email":"lupeicai@tencentmusic.com"},{"name":"刘学","e_name":"mistyliu","email":"mistyliu@tencent.com"},{"name":"何澜欣","e_name":"joehe","email":"joehe@kugou.net"},{"name":"张新想","e_name":"xinxzhang","email":"xinxzhang@kugou.net"},{"name":"白雪纯","e_name":"xuechunbai","email":"xuechunbai@kugou.net"},{"name":"吴晓韵","e_name":"xiaoyunwu","email":"xiaoyunwu@kugou.net"},{"name":"陈恒全","e_name":"charleschen","email":"charleschen@kugou.net"},{"name":"陈子潇","e_name":"brodeychen","email":"brodeychen@kugou.net"},{"name":"杨天圆","e_name":"chovyyang","email":"chovyyang@kugou.net"},{"name":"王云坤","e_name":"yunkunwwang","email":"yunkunwwang@tencentmusic.com"},{"name":"何嘉霖","e_name":"jalenhe","email":"jalenhe@kugou.net"},{"name":"姚沁","e_name":"qinyao","email":"qinyao@kugou.net"},{"name":"徐成智","e_name":"collinxu","email":"collinxu@kugou.net"},{"name":"罗禄宗","e_name":"millsluo","email":"millsluo@tencentmusic.com"},{"name":"谢声儒","e_name":"cyrilxie","email":"cyrilxie@kugou.net"},{"name":"陈兆旭","e_name":"lionelchen","email":"lionelchen@kugou.net"}]
